{
  "env": "finance",
  "model_provider": "openai",
  "model": "gpt-4o-mini",
  "num_trials": 3,
  "temperature": 1,
  "interface_num": 5,
  "task": {
    "user_id": "CUST936948",
    "instruction": "Your user ID is CUST936948. You manage office furniture assets. You want to create five furniture assets: two named 'Office Desk' (with different costs), one 'Conference Table', one 'Ergonomic Chair', and one 'Filing Cabinet'. They were all purchased on 2022-03-15. The first 'Office Desk' costs 800.50 and is located at 'Main HQ NY' from vendor 'Ikea'. The second 'Office Desk' costs 1200.75 and is located at 'Branch Office NJ' from vendor 'Wayfair'. The 'Conference Table' costs 3000.00 and is located at 'Main HQ NY' from 'Staples'. The 'Ergonomic Chair' costs 450.00 and is at 'Branch Office NJ' from 'Herman Miller'. The 'Filing Cabinet' costs 550.00 and is at 'Main HQ NY' from 'OfficeDepot'. From these, dispose of the assets that cost less than 1000. The disposal should be recorded on June 1, 2025 at 2:30 PM UTC. The proceeds for each disposal should be 90% of the asset's original cost.",
    "actions": [
      {
        "name": "create_asset",
        "arguments": {
          "name": "Office Desk",
          "category": "Furniture",
          "purchase_date": "2022-03-15",
          "cost": 800.50,
          "location": "Main HQ NY",
          "vendor": "Ikea",
          "user_id": "CUST936948"
        }
      },
      {
        "name": "create_asset",
        "arguments": {
          "name": "Office Desk",
          "category": "Furniture",
          "purchase_date": "2022-03-15",
          "cost": 1200.75,
          "location": "Branch Office NJ",
          "vendor": "Wayfair",
          "user_id": "CUST936948"
        }
      },
      {
        "name": "create_asset",
        "arguments": {
          "name": "Conference Table",
          "category": "Furniture",
          "purchase_date": "2022-03-15",
          "cost": 3000.00,
          "location": "Main HQ NY",
          "vendor": "Staples",
          "user_id": "CUST936948"
        }
      },
      {
        "name": "create_asset",
        "arguments": {
          "name": "Ergonomic Chair",
          "category": "Furniture",
          "purchase_date": "2022-03-15",
          "cost": 450.00,
          "location": "Branch Office NJ",
          "vendor": "Herman Miller",
          "user_id": "CUST936948"
        }
      },
      {
        "name": "create_asset",
        "arguments": {
          "name": "Filing Cabinet",
          "category": "Furniture",
          "purchase_date": "2022-03-15",
          "cost": 550.00,
          "location": "Main HQ NY",
          "vendor": "OfficeDepot",
          "user_id": "CUST936948"
        }
      },
      {
        "name": "dispose_asset",
        "arguments": {
          "asset_id": "AST-9986",
          "disposed_at": "2025-06-01T14:30:00Z",
          "proceeds": 720.45
        }
      },
      {
        "name": "dispose_asset",
        "arguments": {
          "asset_id": "AST-9989",
          "disposed_at": "2025-06-01T14:30:00Z",
          "proceeds": 405.00
        }
      },
      {
        "name": "dispose_asset",
        "arguments": {
          "asset_id": "AST-9990",
          "disposed_at": "2025-06-01T14:30:00Z",
          "proceeds": 495.00
        }
      }
    ],
    "outputs": [
  "AST-9986",
  "AST-9989",
  "AST-9990"
]
  }
}
