{
    "env": "finance",
    "model_provider": "openai",
    "model": "o4-mini",
    "num_trials": 3,
    "temperature": 1,
    "interface_num": 3,
    "task": {
        "user_id": "CUST969387",
        "instruction": "Your user id is CUST969387. You want to update the unit price on the line item with description 'fact' on your invoice with id INV-250610-Xkgd. The current unit price of 1827.01 on the invoice is incorrect and the correct value is 100. This update on the unit price will change all the calculation and you will want the values on the invoice to be recalculated based. The invoice has 4 units and at 100 per unit, it implies the new value for the amount due will be 400,  line total will be 400,  and with 0.07 tax rate, the  tax amount will be 28 and the total_amount will be 428 resulting. You want all related values on the invoice to be updated accurately based on the calculation.  You will respond reactively to the agent and will not provide any information unless prompted. ",
        "actions": [
            {
                "name": "update_invoice_details",
                "arguments": {
                    "invoice_id": "INV-250610-Xkgd",
                    "updates": {
                        "line_items": [
                          {
                            "description": "fact",
                            "quantity": 4,
                            "unit_price": 100,
                            "line_total": 400
                          }
                        ]
                    }
                }
            }
        ],
        "outputs": [
            "INV-250610-Xkgd",
            "400",
            "428"
        ]
    }
}